aioorm/__init__.py
aioorm/context.py
aioorm/database.py
aioorm/model.py
aioorm/mysql.py
aioorm/postgresql.py
aioorm/query.py
aioorm/result.py
aioorm/shortcuts.py
aioorm/uri_parser.py
aioorm/error/__init__.py
aioorm/error/uri_error.py
aioorm/fields/__init__.py
aioorm/fields/many_to_many_fields.py
aioorm/utils/__init__.py
aioorm/utils/factory_utils.py
aioorm/utils/csv_utils/__init__.py
aioorm/utils/csv_utils/csv_dump.py
aioorm/utils/csv_utils/csv_loader.py
aioorm-0.1.6.data/data/requirements/requirements.txt
aioorm-0.1.6.data/data/requirements/requirements_dev.txt
aioorm-0.1.6.dist-info/DESCRIPTION.rst
aioorm-0.1.6.dist-info/METADATA
aioorm-0.1.6.dist-info/RECORD
aioorm-0.1.6.dist-info/WHEEL
aioorm-0.1.6.dist-info/metadata.json
aioorm-0.1.6.dist-info/top_level.txt
