Metadata-Version: 2.0
Name: aioorm
Version: 0.1.6
Summary: a simple orm suport asyncio,fork of aiopeewee
Home-page: https://github.com/Python-Tools/aioorm
Author: hsz
Author-email: hsz1273327@gmail.com
License: Mozilla
Keywords: orm,asyncio,peewee
Platform: UNKNOWN
Classifier: Development Status :: 3 - Alpha
Classifier: Intended Audience :: Developers
Classifier: Programming Language :: Python :: 3.5
Classifier: Programming Language :: Python :: 3.6
Classifier: Topic :: Documentation :: Sphinx
Requires-Dist: peewee (==2.10.2)
Requires-Dist: aiopg
Requires-Dist: aiomysql
Requires-Dist: aitertools
Requires-Dist: aiofiles
Requires-Dist: async-timeout
Provides-Extra: dev
Requires-Dist: coverage; extra == 'dev'
Requires-Dist: mypy; extra == 'dev'
Requires-Dist: mypy-extensions; extra == 'dev'
Requires-Dist: lxml; extra == 'dev'
Requires-Dist: wheel; extra == 'dev'
Requires-Dist: pydocstyle; extra == 'dev'
Requires-Dist: pep8; extra == 'dev'
Requires-Dist: autopep8; extra == 'dev'
